AIAgent/Examples/DateTimeTools.py
AIAgent/Examples/ImageTool.py
AIAgent/Examples/PlaywrightMCP.py
AIAgent/Examples/WeatherTools.py
AIAgent/Examples/__init__.py
robotframework_aiagent_examples-0.0.1.dist-info/METADATA
robotframework_aiagent_examples-0.0.1.dist-info/WHEEL
robotframework_aiagent_examples-0.0.1.dist-info/entry_points.txt
robotframework_aiagent_examples-0.0.1.dist-info/RECORD
