Metadata-Version: 2.4
Name: robotframework-aiagent-examples
Version: 0.0.1
Dynamic: Requires-Dist
Dynamic: Provides-Extra
Summary: robotframework-aiagent examples
Requires-Python: >=3.10
Requires-Dist: robotframework-aiagent-slim[anthropic,openai]==0.0.0
